fuclib/__init__.py
fuclib/zlcollector.py
zlcollector-0.0.1.dist-info/METADATA
zlcollector-0.0.1.dist-info/WHEEL
zlcollector-0.0.1.dist-info/top_level.txt
zlcollector-0.0.1.dist-info/RECORD
