Metadata-Version: 2.1
Name: zlcollector
Version: 0.0.1
Summary: This is a method library that I wrote for zhulong_spiders.
Home-page: https://elanpy.com
Author: eamonn
Author-email: china.eamonn@gmail.com
License: MIT
Platform: UNKNOWN
Classifier: License :: OSI Approved :: MIT License
Classifier: Programming Language :: Python
Classifier: Programming Language :: Python :: 3
Classifier: Programming Language :: Python :: 3.6
Classifier: Programming Language :: Python :: Implementation :: CPython
Classifier: Programming Language :: Python :: Implementation :: PyPy
Requires-Python: >=3.4.0
